spitzer/__init__.py
spitzer/__main__.py
spitzer/settings.py
spitzer/lib/__init__.py
spitzer/lib/main.py
spitzer/lib/config/__init__.py
spitzer/lib/config/loader.py
spitzer/lib/config/parser.py
spitzer/lib/config/validator.py
spitzer/lib/core/__init__.py
spitzer/lib/core/connection.py
spitzer/lib/core/create.py
spitzer/lib/core/install.py
spitzer/lib/core/make_migrations.py
spitzer/lib/core/migrate.py
spitzer/lib/core/migrations.py
spitzer/lib/core/reader.py
spitzer/lib/core/rollback.py
spitzer/lib/drivers/__init__.py
spitzer/lib/drivers/connector.py
spitzer/lib/models/__init__.py
spitzer/lib/models/spitzer_migrations.py
spitzer-1.1.0.dist-info/DESCRIPTION.rst
spitzer-1.1.0.dist-info/METADATA
spitzer-1.1.0.dist-info/RECORD
spitzer-1.1.0.dist-info/WHEEL
spitzer-1.1.0.dist-info/metadata.json
spitzer-1.1.0.dist-info/top_level.txt
