Metadata-Version: 2.0
Name: spitzer
Version: 1.1.0
Summary: Django-based multi-target migration tool
Home-page: https://github.com/feliphebueno/Spitzer
Author: Rinzler
Author-email: feliphezion@gmail.com
License: MIT
Keywords: migration,database,devops
Platform: UNKNOWN
Classifier: Development Status :: 3 - Alpha
Classifier: Intended Audience :: Developers
Classifier: Topic :: Software Development
Classifier: License :: OSI Approved :: MIT License
Classifier: Programming Language :: Python :: 2
Classifier: Programming Language :: Python :: 2.7
Classifier: Programming Language :: Python :: 3
Classifier: Programming Language :: Python :: 3.3
Classifier: Programming Language :: Python :: 3.4
Classifier: Programming Language :: Python :: 3.5
Requires-Dist: Django
Requires-Dist: PyYAML
Requires-Dist: cymysql
Requires-Dist: django-cymysql
Requires-Dist: terminaltables
Provides-Extra: dev
Requires-Dist: check-manifest; extra == 'dev'
Provides-Extra: test
Requires-Dist: coverage; extra == 'test'
